{
  "sectionCode": "524",
  "mappings": [
    {
      "articleTitle": "Urbanization",
      "relevantPathsAI": [
        "B",
        "B.1",
        "B.2",
        "B.4",
        "B.4.a",
        "B.4.b",
        "B.4.e",
        "B.4.f"
      ],
      "rationaleAI": "Global demographic shift covering characteristics of urbanization (B.1), historical urbanization (B.2), megalopolis formation (B.4.a), suburbanization (B.4.b), problems of urban growth (B.4.e), and environmental change including pollution (B.4.f)."
    },
    {
      "articleTitle": "City",
      "relevantPathsAI": [
        "B",
        "B.1",
        "B.2",
        "B.3"
      ],
      "rationaleAI": "Dense non-agricultural settlement covering characteristics of urbanization (B.1), historical evolution (B.2), and urban planning and redevelopment (B.3)."
    },
    {
      "articleTitle": "Cairo",
      "relevantPathsAI": [
        "B.2",
        "B.4.e"
      ],
      "rationaleAI": "Africa's largest city with historical development from Fatimid founding through modern expansion (B.2), facing contemporary challenges of pollution and traffic (B.4.e)."
    },
    {
      "articleTitle": "Lagos",
      "relevantPathsAI": [
        "B.2",
        "B.4.a",
        "B.4.e"
      ],
      "rationaleAI": "Africa's most populous urban area representing history of urbanization (B.2), emerging Abidjan-Lagos megalopolis (B.4.a), and rapid urban growth challenges (B.4.e)."
    },
    {
      "articleTitle": "Beijing",
      "relevantPathsAI": [
        "B.2"
      ],
      "rationaleAI": "China's political center for eight centuries, representing the history of urbanization (B.2) with continuous imperial and modern development."
    },
    {
      "articleTitle": "Karl Marx",
      "relevantPathsAI": [
        "A.3.e"
      ],
      "rationaleAI": "Marxist population theory addressing the relationship between capitalism, labor, and demographic movements (A.3.e)."
    },
    {
      "articleTitle": "Tokyo",
      "relevantPathsAI": [
        "B.2",
        "B.4.a"
      ],
      "rationaleAI": "World's most populous metropolitan area representing the history of urbanization (B.2) and megalopolis formation with 41 million residents (B.4.a)."
    },
    {
      "articleTitle": "Bangkok",
      "relevantPathsAI": [
        "B.2",
        "B.4.e"
      ],
      "rationaleAI": "Southeast Asian megacity dominating Thailand's political and economic life (B.2), with chronic traffic congestion and haphazard growth as urban problems (B.4.e)."
    },
    {
      "articleTitle": "Delhi",
      "relevantPathsAI": [
        "B.2",
        "B.4.e",
        "B.4.f"
      ],
      "rationaleAI": "Second-largest global metropolitan area with medieval through modern development (B.2), facing air pollution (B.4.f) and urban sprawl challenges (B.4.e)."
    },
    {
      "articleTitle": "Mumbai",
      "relevantPathsAI": [
        "B.2",
        "B.4.e"
      ],
      "rationaleAI": "India's financial capital with colonial development history (B.2) and ongoing challenges of informal settlements and infrastructure (B.4.e)."
    },
    {
      "articleTitle": "New York City",
      "relevantPathsAI": [
        "B.2",
        "B.4.a"
      ],
      "rationaleAI": "World's largest metropolitan economy with Dutch colonial origins (B.2), representing coalescence of metropolitan financial, cultural, and diplomatic functions (B.4.a)."
    },
    {
      "articleTitle": "Ecology",
      "relevantPathsAI": [
        "A.3.g"
      ],
      "rationaleAI": "Scientific study of organism-environment relationships, providing the framework for ecological theories of population-resource conservation (A.3.g)."
    },
    {
      "articleTitle": "Globalization",
      "relevantPathsAI": [
        "B.4.c",
        "B.4.d"
      ],
      "rationaleAI": "Intensifying global interdependence driving regional economic integration between cities and hinterlands (B.4.c) and extending urban dominance through technology (B.4.d)."
    },
    {
      "articleTitle": "Singapore",
      "relevantPathsAI": [
        "B.2",
        "B.4.d"
      ],
      "rationaleAI": "Island city-state representing urbanization history (B.2) and the role of technology in extending urban economic dominance (B.4.d)."
    },
    {
      "articleTitle": "Istanbul",
      "relevantPathsAI": [
        "B.2"
      ],
      "rationaleAI": "Turkey's largest city straddling Europe and Asia, with three millennia of urbanization history from Byzantium through Ottoman to modern eras (B.2)."
    },
    {
      "articleTitle": "Paris",
      "relevantPathsAI": [
        "B.2",
        "B.3"
      ],
      "rationaleAI": "European global city shaped by Haussmann's 19th-century urban renovations (B.3), representing long-term urbanization history (B.2)."
    },
    {
      "articleTitle": "Human migration",
      "relevantPathsAI": [
        "A.1.c"
      ],
      "rationaleAI": "Movement of people between locations, directly constituting migration and refugee movements as a determinant of population (A.1.c)."
    },
    {
      "articleTitle": "Transport",
      "relevantPathsAI": [
        "B.4.d"
      ],
      "rationaleAI": "Movement systems organized around infrastructure and vehicles, relevant to the role of technology in extending urban dominance and influence (B.4.d)."
    },
    {
      "articleTitle": "Information Age",
      "relevantPathsAI": [
        "B.4.d"
      ],
      "rationaleAI": "Shift to IT-centered economies extending urban influence through digital networks (B.4.d)."
    },
    {
      "articleTitle": "Hong Kong",
      "relevantPathsAI": [
        "B.2",
        "B.4.c"
      ],
      "rationaleAI": "Special Administrative Region as a global financial center (B.2), representing regional economic integration between city and hinterland (B.4.c)."
    },
    {
      "articleTitle": "Jakarta",
      "relevantPathsAI": [
        "B.2",
        "B.4.e"
      ],
      "rationaleAI": "Indonesia's capital with colonial history (B.2), facing severe challenges of flooding, air pollution, and land subsidence prompting capital relocation (B.4.e)."
    },
    {
      "articleTitle": "London",
      "relevantPathsAI": [
        "B.2",
        "B.4.a"
      ],
      "rationaleAI": "UK's primate city with Roman origins (B.2), metropolitan population of ~15 million and Europe's largest city economy representing megalopolis formation (B.4.a)."
    },
    {
      "articleTitle": "São Paulo",
      "relevantPathsAI": [
        "B.1",
        "B.4.a"
      ],
      "rationaleAI": "São Paulo Macrometropolis (~30 million) is explicitly identified as the Southern Hemisphere's first megalopolis, directly covering B.4.a; the city also illustrates B.1 characteristics of rapid 20th-century Latin American urbanization."
    },
    {
      "articleTitle": "Pollution",
      "relevantPathsAI": [
        "B.4.f"
      ],
      "rationaleAI": "Introduction of harmful contaminants from human activities, directly constituting problems of environmental change including pollution and climatic change (B.4.f)."
    },
    {
      "articleTitle": "Human settlement",
      "relevantPathsAI": [
        "B",
        "B.1"
      ],
      "rationaleAI": "Communities of people from homesteads to megacities, covering the full scale of urban settlement complexity and characteristics of urbanization (B.1)."
    },
    {
      "articleTitle": "Africa",
      "relevantPathsAI": [
        "A.5",
        "B.4"
      ],
      "rationaleAI": "Youngest continent population with urbanization growth concentrated in Africa (A.5), facing infrastructure and environmental challenges of rapid urban expansion (B.4)."
    },
    {
      "articleTitle": "Architecture",
      "relevantPathsAI": [
        "B.3.a"
      ],
      "rationaleAI": "Design and construction of structures, providing methods and materials of urban planning and redevelopment (B.3.a)."
    },
    {
      "articleTitle": "Agriculture",
      "relevantPathsAI": [
        "A.3.g"
      ],
      "rationaleAI": "Cultivation of crops and livestock relevant to ecological theories concerning population growth and natural resource conservation (A.3.g)."
    },
    {
      "articleTitle": "Black Death",
      "relevantPathsAI": [
        "A.2"
      ],
      "rationaleAI": "Plague pandemic killing 30-60% of Europe's population, representing a dramatic historical change in population through catastrophic mortality (A.2)."
    },
    {
      "articleTitle": "Ibn Khaldun",
      "relevantPathsAI": [
        "A.3",
        "B.2"
      ],
      "rationaleAI": "Proto-macroeconomic and sociological analysis of nomadic vs. sedentary civilizations relevant to theories of population (A.3) and the cyclical rise of urban centers (B.2)."
    }
  ],
  "_curatedBy": "ai",
  "_generatedAt": "2026-03-23"
}
