{
  "partNumber": 10,
  "readings": {
    "vsi": [
      {
        "title": "Information",
        "count": 4,
        "sections": 4,
        "paths": 5,
        "author": "Luciano Floridi",
        "relevance": 100
      },
      {
        "title": "Aristotle",
        "count": 4,
        "sections": 7,
        "paths": 9,
        "author": "Jonathan Barnes",
        "relevance": 99
      },
      {
        "title": "Computer Science",
        "count": 4,
        "sections": 5,
        "paths": 7,
        "author": "Subrata Dasgupta",
        "relevance": 97
      },
      {
        "title": "Descartes",
        "count": 4,
        "sections": 5,
        "paths": 7,
        "author": "Tom Sorell",
        "relevance": 97
      },
      {
        "title": "Plato",
        "count": 4,
        "sections": 5,
        "paths": 6,
        "author": "Julia Annas",
        "relevance": 97
      },
      {
        "title": "Leibniz",
        "count": 3,
        "sections": 5,
        "paths": 6,
        "author": "Maria Rosa Antognazza",
        "relevance": 77
      },
      {
        "title": "Logic",
        "count": 3,
        "sections": 5,
        "paths": 6,
        "author": "Graham Priest",
        "relevance": 77
      },
      {
        "title": "Russell",
        "count": 3,
        "sections": 5,
        "paths": 5,
        "author": "A. C. Grayling",
        "relevance": 77
      },
      {
        "title": "Infinity",
        "count": 3,
        "sections": 4,
        "paths": 5,
        "author": "Ian Stewart",
        "relevance": 75
      },
      {
        "title": "Philosophy in the Islamic World",
        "count": 3,
        "sections": 4,
        "paths": 5,
        "author": "Peter Adamson",
        "relevance": 75
      },
      {
        "title": "Presocratic Philosophy",
        "count": 3,
        "sections": 4,
        "paths": 5,
        "author": "Catherine Osborne",
        "relevance": 75
      },
      {
        "title": "The Computer",
        "count": 3,
        "sections": 4,
        "paths": 5,
        "author": "Darrel Ince",
        "relevance": 75
      },
      {
        "title": "The History of Computing",
        "count": 3,
        "sections": 4,
        "paths": 5,
        "author": "Doron Swade",
        "relevance": 75
      },
      {
        "title": "Thomas Aquinas",
        "count": 3,
        "sections": 4,
        "paths": 5,
        "author": "Fergus Kerr",
        "relevance": 75
      },
      {
        "title": "Ancient philosophy",
        "count": 3,
        "sections": 4,
        "paths": 4,
        "author": "Julia Annas",
        "relevance": 75
      },
      {
        "title": "Geography",
        "count": 3,
        "sections": 4,
        "paths": 4,
        "author": "John A. Matthews, David T. Herbert",
        "relevance": 75
      },
      {
        "title": "Indian philosophy",
        "count": 3,
        "sections": 4,
        "paths": 4,
        "author": "Sue Hamilton",
        "relevance": 75
      },
      {
        "title": "Kant",
        "count": 3,
        "sections": 4,
        "paths": 4,
        "author": "Roger Scruton",
        "relevance": 75
      },
      {
        "title": "Meaning",
        "count": 3,
        "sections": 4,
        "paths": 4,
        "author": "Emma Borg and Sarah A. Fisher",
        "relevance": 75
      },
      {
        "title": "Medieval Philosophy",
        "count": 3,
        "sections": 4,
        "paths": 4,
        "author": "John Marenbon",
        "relevance": 75
      },
      {
        "title": "Continental philosophy",
        "count": 3,
        "sections": 5,
        "paths": 6,
        "author": "Simon Critchley",
        "relevance": 71
      }
    ],
    "wiki": [
      {
        "title": "Islamic Golden Age",
        "count": 6,
        "sections": 11,
        "paths": 13,
        "relevance": 100
      },
      {
        "title": "René Descartes",
        "count": 5,
        "sections": 7,
        "paths": 16,
        "relevance": 88
      },
      {
        "title": "Artificial intelligence",
        "count": 4,
        "sections": 4,
        "paths": 9,
        "relevance": 79
      },
      {
        "title": "Kurt Gödel",
        "count": 4,
        "sections": 7,
        "paths": 18,
        "relevance": 79
      },
      {
        "title": "Aristotle",
        "count": 4,
        "sections": 8,
        "paths": 18,
        "relevance": 78
      },
      {
        "title": "Ancient Greece",
        "count": 4,
        "sections": 8,
        "paths": 15,
        "relevance": 78
      },
      {
        "title": "Renaissance",
        "count": 4,
        "sections": 8,
        "paths": 11,
        "relevance": 77
      },
      {
        "title": "Age of Enlightenment",
        "count": 4,
        "sections": 9,
        "paths": 23,
        "relevance": 77
      },
      {
        "title": "Isaac Newton",
        "count": 4,
        "sections": 6,
        "paths": 12,
        "relevance": 77
      },
      {
        "title": "Western philosophy",
        "count": 4,
        "sections": 5,
        "paths": 21,
        "relevance": 77
      },
      {
        "title": "Epistemology",
        "count": 4,
        "sections": 5,
        "paths": 18,
        "relevance": 77
      },
      {
        "title": "Scientific method",
        "count": 4,
        "sections": 5,
        "paths": 17,
        "relevance": 77
      },
      {
        "title": "Mathematics",
        "count": 4,
        "sections": 5,
        "paths": 15,
        "relevance": 77
      },
      {
        "title": "Alan Turing",
        "count": 4,
        "sections": 5,
        "paths": 13,
        "relevance": 77
      },
      {
        "title": "History of science",
        "count": 4,
        "sections": 9,
        "paths": 28,
        "relevance": 76
      },
      {
        "title": "History of mathematics",
        "count": 4,
        "sections": 7,
        "paths": 31,
        "relevance": 75
      },
      {
        "title": "History of philosophy",
        "count": 4,
        "sections": 7,
        "paths": 26,
        "relevance": 75
      },
      {
        "title": "Reason",
        "count": 4,
        "sections": 7,
        "paths": 17,
        "relevance": 75
      },
      {
        "title": "Avicenna",
        "count": 4,
        "sections": 7,
        "paths": 14,
        "relevance": 75
      },
      {
        "title": "Philosophy",
        "count": 4,
        "sections": 6,
        "paths": 13,
        "relevance": 73
      },
      {
        "title": "Scientific Revolution",
        "count": 4,
        "sections": 7,
        "paths": 13,
        "relevance": 69
      },
      {
        "title": "Logic",
        "count": 3,
        "sections": 5,
        "paths": 16,
        "relevance": 61
      },
      {
        "title": "Mathematical proof",
        "count": 3,
        "sections": 5,
        "paths": 12,
        "relevance": 61
      },
      {
        "title": "Galileo Galilei",
        "count": 3,
        "sections": 5,
        "paths": 10,
        "relevance": 61
      },
      {
        "title": "Ibn Khaldun",
        "count": 3,
        "sections": 5,
        "paths": 8,
        "relevance": 61
      },
      {
        "title": "Computer",
        "count": 3,
        "sections": 4,
        "paths": 11,
        "relevance": 60
      },
      {
        "title": "Karl Marx",
        "count": 3,
        "sections": 4,
        "paths": 9,
        "relevance": 60
      },
      {
        "title": "Sigmund Freud",
        "count": 3,
        "sections": 4,
        "paths": 9,
        "relevance": 60
      },
      {
        "title": "Education",
        "count": 3,
        "sections": 4,
        "paths": 6,
        "relevance": 60
      },
      {
        "title": "Immanuel Kant",
        "count": 3,
        "sections": 5,
        "paths": 12,
        "relevance": 56
      },
      {
        "title": "Niccolò Machiavelli",
        "count": 3,
        "sections": 5,
        "paths": 9,
        "relevance": 56
      }
    ],
    "macro": [
      {
        "title": "Philosophies of the Branches of Knowledge",
        "count": 5,
        "sections": 7,
        "paths": 7,
        "relevance": 100
      },
      {
        "title": "Locke",
        "count": 2,
        "sections": 2,
        "paths": 2,
        "relevance": 45
      },
      {
        "title": "Pascal",
        "count": 2,
        "sections": 2,
        "paths": 2,
        "relevance": 45
      },
      {
        "title": "Marxism, Marx and",
        "count": 2,
        "sections": 3,
        "paths": 3,
        "relevance": 43
      },
      {
        "title": "Smith, Adam",
        "count": 2,
        "sections": 3,
        "paths": 3,
        "relevance": 43
      }
    ]
  }
}
